quicolor/__init__.py
quicolor-10.0.9.dist-info/licenses/LICENSE
quicolor-10.0.9.dist-info/METADATA
quicolor-10.0.9.dist-info/WHEEL
quicolor-10.0.9.dist-info/top_level.txt
quicolor-10.0.9.dist-info/RECORD
