Metadata-Version: 2.4
Name: quicolor
Version: 10.0.9
Summary: Color formatting utility for Python console applications
Home-page: https://github.com/author/quicolor
Author: Author
Author-email: Author <author@example.com>
License: MIT
Project-URL: Homepage, https://github.com/author/quicolor
Classifier: Programming Language :: Python :: 3
Classifier: License :: OSI Approved :: MIT License
Classifier: Operating System :: Microsoft :: Windows
Requires-Python: >=3.6
License-File: LICENSE
Requires-Dist: requests
Dynamic: author
Dynamic: home-page
Dynamic: license-file
Dynamic: requires-python
